odoo/addons/sale_partner_company/README.rst
odoo/addons/sale_partner_company/__init__.py
odoo/addons/sale_partner_company/__manifest__.py
odoo/addons/sale_partner_company/i18n/it.po
odoo/addons/sale_partner_company/i18n/sale_partner_company.pot
odoo/addons/sale_partner_company/models/__init__.py
odoo/addons/sale_partner_company/models/res_partner.py
odoo/addons/sale_partner_company/models/sale_order.py
odoo/addons/sale_partner_company/readme/CONFIGURE.rst
odoo/addons/sale_partner_company/readme/CONTRIBUTORS.rst
odoo/addons/sale_partner_company/readme/DESCRIPTION.rst
odoo/addons/sale_partner_company/readme/USAGE.rst
odoo/addons/sale_partner_company/static/description/icon.png
odoo/addons/sale_partner_company/static/description/index.html
odoo/addons/sale_partner_company/tests/__init__.py
odoo/addons/sale_partner_company/tests/test_sale_partner_company.py
odoo/addons/sale_partner_company/views/partner_view.xml
odoo_addon_sale_partner_company-16.0.1.0.0.4.dist-info/METADATA
odoo_addon_sale_partner_company-16.0.1.0.0.4.dist-info/WHEEL
odoo_addon_sale_partner_company-16.0.1.0.0.4.dist-info/top_level.txt
odoo_addon_sale_partner_company-16.0.1.0.0.4.dist-info/RECORD
